templateco/.DS_Store
templateco/PLUGIN.md
templateco/README.md
templateco/__init__.py
templateco/exceptions.py
templateco/output.py
templateco/plugin.py
templateco/py.typed
templateco/pyproject.toml
templateco/templateco.py
templateco/typing.py
templateco-0.1.6.dist-info/WHEEL
templateco-0.1.6.dist-info/METADATA
templateco-0.1.6.dist-info/RECORD
